[
  {
    "timestamp": "20241015-210001",
    "temperature": "11.3",
    "humidity": "82",
    "windSpeed": "1.3",
    "gustSpeed": "2.0",
    "rain": "113.1",
    "windDirection": "180.0"
  },
  {
    "timestamp": "20241015-220001",
    "temperature": "11.6",
    "humidity": "77",
    "windSpeed": "3.0",
    "gustSpeed": "4.0",
    "rain": "113.1",
    "windDirection": "90.0"
  },
  {
    "timestamp": "20241015-230001",
    "temperature": "11.3",
    "humidity": "78",
    "windSpeed": "2.3",
    "gustSpeed": "4.4",
    "rain": "113.1",
    "windDirection": "135.0"
  },
  {
    "timestamp": "20241016-000001",
    "temperature": "11.1",
    "humidity": "77",
    "windSpeed": "3.7",
    "gustSpeed": "4.7",
    "rain": "113.1",
    "windDirection": "135.0"
  },
  {
    "timestamp": "20241016-010002",
    "temperature": "11.0",
    "humidity": "78",
    "windSpeed": "2.0",
    "gustSpeed": "2.7",
    "rain": "113.1",
    "windDirection": "90.0"
  },
  {
    "timestamp": "20241016-020001",
    "temperature": "10.3",
    "humidity": "80",
    "windSpeed": "2.7",
    "gustSpeed": "3.7",
    "rain": "113.1",
    "windDirection": "135.0"
  },
  {
    "timestamp": "20241016-030001",
    "temperature": "9.9",
    "humidity": "82",
    "windSpeed": "2.0",
    "gustSpeed": "2.7",
    "rain": "113.1",
    "windDirection": "135.0"
  },
  {
    "timestamp": "20241016-040001",
    "temperature": "9.3",
    "humidity": "84",
    "windSpeed": "2.0",
    "gustSpeed": "2.7",
    "rain": "113.1",
    "windDirection": "90.0"
  },
  {
    "timestamp": "20241016-050001",
    "temperature": "9.0",
    "humidity": "86",
    "windSpeed": "1.7",
    "gustSpeed": "2.3",
    "rain": "113.1",
    "windDirection": "135.0"
  },
  {
    "timestamp": "20241016-060001",
    "temperature": "8.9",
    "humidity": "87",
    "windSpeed": "1.3",
    "gustSpeed": "2.3",
    "rain": "113.1",
    "windDirection": "135.0"
  },
  {
    "timestamp": "20241016-070001",
    "temperature": "9.1",
    "humidity": "88",
    "windSpeed": "1.3",
    "gustSpeed": "1.7",
    "rain": "113.1",
    "windDirection": "135.0"
  },
  {
    "timestamp": "20241016-080001",
    "temperature": "9.1",
    "humidity": "88",
    "windSpeed": "1.3",
    "gustSpeed": "1.7",
    "rain": "113.1",
    "windDirection": "135.0"
  },
  {
    "timestamp": "20241016-090001",
    "temperature": "9.1",
    "humidity": "88",
    "windSpeed": "1.3",
    "gustSpeed": "1.7",
    "rain": "113.1",
    "windDirection": "135.0"
  },
  {
    "timestamp": "20241016-100001",
    "temperature": "11.7",
    "humidity": "86",
    "windSpeed": "1.3",
    "gustSpeed": "1.7",
    "rain": "113.1",
    "windDirection": "135.0"
  },
  {
    "timestamp": "20241016-110001",
    "temperature": "14.9",
    "humidity": "77",
    "windSpeed": "1.0",
    "gustSpeed": "1.3",
    "rain": "113.1",
    "windDirection": "135.0"
  },
  {
    "timestamp": "20241016-120002",
    "temperature": "16.0",
    "humidity": "76",
    "windSpeed": "1.3",
    "gustSpeed": "2.3",
    "rain": "113.1",
    "windDirection": "135.0"
  },
  {
    "timestamp": "20241016-130001",
    "temperature": "19.7",
    "humidity": "63",
    "windSpeed": "5.1",
    "gustSpeed": "6.4",
    "rain": "113.1",
    "windDirection": "180.0"
  },
  {
    "timestamp": "20241016-140001",
    "temperature": "20.2",
    "humidity": "62",
    "windSpeed": "5.4",
    "gustSpeed": "6.4",
    "rain": "113.1",
    "windDirection": "135.0"
  },
  {
    "timestamp": "20241016-150001",
    "temperature": "20.2",
    "humidity": "64",
    "windSpeed": "3.4",
    "gustSpeed": "3.7",
    "rain": "113.1",
    "windDirection": "135.0"
  },
  {
    "timestamp": "20241016-160001",
    "temperature": "20.5",
    "humidity": "66",
    "windSpeed": "1.7",
    "gustSpeed": "2.3",
    "rain": "113.1",
    "windDirection": "157.5"
  },
  {
    "timestamp": "20241016-170001",
    "temperature": "20.4",
    "humidity": "71",
    "windSpeed": "1.0",
    "gustSpeed": "1.3",
    "rain": "113.1",
    "windDirection": "135.0"
  },
  {
    "timestamp": "20241016-180001",
    "temperature": "19.7",
    "humidity": "70",
    "windSpeed": "1.7",
    "gustSpeed": "2.3",
    "rain": "113.1",
    "windDirection": "135.0"
  },
  {
    "timestamp": "20241016-190001",
    "temperature": "18.2",
    "humidity": "74",
    "windSpeed": "2.3",
    "gustSpeed": "3.0",
    "rain": "113.1",
    "windDirection": "180.0"
  },
  {
    "timestamp": "20241016-200001",
    "temperature": "17.6",
    "humidity": "73",
    "windSpeed": "1.0",
    "gustSpeed": "1.3",
    "rain": "113.1",
    "windDirection": "135.0"
  }
]